barwex_bashrc/__init__.py
barwex_bashrc/bashrcio.py
barwex_bashrc/main.py
barwex_bashrc/data/base.sh
barwex_bashrc/data/docker.sh
barwex_bashrc/data/ps1.sh
barwex_bashrc/data/screen.sh
barwex_bashrc-0.2.dist-info/METADATA
barwex_bashrc-0.2.dist-info/WHEEL
barwex_bashrc-0.2.dist-info/entry_points.txt
barwex_bashrc-0.2.dist-info/top_level.txt
barwex_bashrc-0.2.dist-info/RECORD
