Metadata-Version: 2.1
Name: barwex-bashrc
Version: 0.2
Summary: This is an application automatically generated by barwex-startapp
Home-page: 
Author: barwe
Author-email: barwechin@163.com
Requires-Python: >=3.9
Requires-Dist: xuse >=0.4.4
